{
  "project_info": {
    "project_number": "904973056641",
    "project_id": "the-screams-of-kainarah",
    "storage_bucket": "the-screams-of-kainarah.appspot.com"
  },
  "client": [
    {
      "client_info": {
        "mobilesdk_app_id": "1:904973056641:android:cee24d88689c05290beb80",
        "android_client_info": {
          "package_name": "com.mb.screamsofkainarah"
        }
      },
      "oauth_client": [],
      "api_key": [
        {
          "current_key": "AIzaSyCij35-bW4H-y4ybqdrq1DK8wOL89T8sD8"
        }
      ],
      "services": {
        "appinvite_service": {
          "other_platform_oauth_client": []
        }
      }
    }
  ],
  "configuration_version": "1"
}